mrols/__init__.py
mrols/analyser.py
mrols/calculator.py
mrols/mro_lang_server.py
mrols/parsed_class.py
mrols/parsed_custom_class.py
mrols/parsed_package_class.py
mrols/server.py
python_mro_language_server-0.0.1.dist-info/LICENSE
python_mro_language_server-0.0.1.dist-info/METADATA
python_mro_language_server-0.0.1.dist-info/WHEEL
python_mro_language_server-0.0.1.dist-info/top_level.txt
python_mro_language_server-0.0.1.dist-info/RECORD
