Metadata-Version: 2.1
Name: python-mro-language-server
Version: 0.0.1
Summary: A simple Python language server to provide MRO (Method Resolution Order) inference via Hover and CodeLens.
Home-page: https://github.com/mosckital/python-mro-language-server
Author: Kaiyan XIAO
Author-email: k.max.xiao@gmail.com
License: MIT
Keywords: MRO,language-server,method-resolution-order,syntax-analysis
Platform: UNKNOWN
Classifier: Development Status :: 3 - Alpha
Classifier: License :: OSI Approved :: MIT License
Classifier: Programming Language :: Python :: 3.6
Classifier: Programming Language :: Python :: 3.7
Classifier: Programming Language :: Python :: 3.8
Classifier: Operating System :: OS Independent
Requires-Python: >=3.6
Requires-Dist: jedi (==0.18.0)
Requires-Dist: python-jsonrpc-server (==0.4.0)
Requires-Dist: parso (==0.8.1) ; python_version >= "3.6"
Requires-Dist: ujson (==4.0.2) ; python_version >= "3.6"
